drowzee/__init__.py
drowzee/courses.py
drowzee/utils.py
drowzee-0.1.1.dist-info/METADATA
drowzee-0.1.1.dist-info/WHEEL
drowzee-0.1.1.dist-info/top_level.txt
drowzee-0.1.1.dist-info/RECORD
