Metadata-Version: 2.1
Name: drowzee
Version: 0.1.1
Summary: Una biblioteca para consultar cursos de hack4u.
Home-page: https://hack4u.io
Author: Ubaldo Jóse
